openstl.cpython-38-x86_64-linux-gnu.so
openstl.libs/libstdc++-496613c0.so.6.0.32
openstl.libs/libgcc_s-a3a07607.so.1
openstl-4.0.1.dist-info/LICENSE
openstl-4.0.1.dist-info/WHEEL
openstl-4.0.1.dist-info/top_level.txt
openstl-4.0.1.dist-info/METADATA
openstl-4.0.1.dist-info/RECORD
